repytah/__init__.py
repytah/assemble.py
repytah/example.py
repytah/search.py
repytah/transform.py
repytah/utilities.py
repytah/version.py
repytah/data/README.md
repytah/data/input.csv
repytah/data/mazurka30-1.csv
repytah/data/mazurka30-3.csv
repytah-0.1.2.dist-info/AUTHORS.md
repytah-0.1.2.dist-info/LICENSE.md
repytah-0.1.2.dist-info/METADATA
repytah-0.1.2.dist-info/WHEEL
repytah-0.1.2.dist-info/top_level.txt
repytah-0.1.2.dist-info/RECORD
