Metadata-Version: 2.1
Name: repytah
Version: 0.1.2
Summary: Python package for building Aligned Hierarchies for sequential data streams
Home-page: https://github.com/smith-tinkerlab/repytah
Author: Smith Tinker Lab, Katherine M. Kinnaird (PI)
Author-email: tinkerlab@smith.edu
License: ISC
Project-URL: Bug Reports, https://github.com/smith-tinkerlab/repytah/issues
Project-URL: Source, https://github.com/smith-tinkerlab/repytah
Classifier: Development Status :: 3 - Alpha
Classifier: Intended Audience :: Developers
Classifier: License :: OSI Approved :: ISC License (ISCL)
Classifier: Topic :: Multimedia :: Sound/Audio :: Analysis
Classifier: Programming Language :: Python :: 3.7
Classifier: Programming Language :: Python :: 3.8
Classifier: Programming Language :: Python :: 3.9
Classifier: Programming Language :: Python :: 3.10
Requires-Python: >=3.7, <4
License-File: LICENSE.md
License-File: AUTHORS.md
Requires-Dist: numpy (>=1.21.6)
Requires-Dist: scipy (>=1.7.3)
Requires-Dist: pandas (>=1.3.5)
Requires-Dist: matplotlib (>=3.3.4)
Requires-Dist: opencv-python (>=4.5.0)
Requires-Dist: setuptools (>=61.2.0)
Provides-Extra: docs
Requires-Dist: sphinx (!=5.0.2) ; extra == 'docs'
Requires-Dist: sphinx-rtd-theme (>=1.0.0) ; extra == 'docs'
Requires-Dist: nbsphinx (==0.8.*) ; extra == 'docs'
Requires-Dist: spyder (>=4.0.0) ; extra == 'docs'
Requires-Dist: numpydoc (>=1.4.0) ; extra == 'docs'
Requires-Dist: myst-parser (==0.15.1) ; extra == 'docs'
Requires-Dist: readthedocs-sphinx-search (==0.1.0) ; extra == 'docs'
Provides-Extra: tests
Requires-Dist: pytest ; extra == 'tests'
